{
  "m_GameObject": {
    "m_FileID": 0,
    "m_PathID": 0
  },
  "m_Enabled": 1,
  "m_Script": {
    "m_FileID": 0,
    "m_PathID": -1253097590706675564
  },
  "m_Name": "CourseMapParam",
  "mMapObjArray": [
    {
      "m_FileID": 17,
      "m_PathID": -7307446656490476645
    },
    {
      "m_FileID": 4,
      "m_PathID": 4754879795219884136
    },
    {
      "m_FileID": 7,
      "m_PathID": -1099803160674548907
    },
    {
      "m_FileID": 6,
      "m_PathID": 5277221653906901017
    },
    {
      "m_FileID": 5,
      "m_PathID": 757040245166943341
    },
    {
      "m_FileID": 3,
      "m_PathID": 7902925131818173625
    },
    {
      "m_FileID": 9,
      "m_PathID": 2780778863115553754
    },
    {
      "m_FileID": 18,
      "m_PathID": 1783806711236351291
    },
    {
      "m_FileID": 13,
      "m_PathID": -7683271295301486976
    },
    {
      "m_FileID": 26,
      "m_PathID": 3089172396742571038
    },
    {
      "m_FileID": 24,
      "m_PathID": 7342577336851685164
    },
    {
      "m_FileID": 16,
      "m_PathID": 3179527181048846069
    },
    {
      "m_FileID": 22,
      "m_PathID": -1290550119096056567
    },
    {
      "m_FileID": 10,
      "m_PathID": 7124423691745270411
    },
    {
      "m_FileID": 8,
      "m_PathID": 3945621986495836585
    },
    {
      "m_FileID": 15,
      "m_PathID": 5661814164476727614
    },
    {
      "m_FileID": 23,
      "m_PathID": 8528134015418398253
    },
    {
      "m_FileID": 11,
      "m_PathID": -1351954998463601693
    },
    {
      "m_FileID": 25,
      "m_PathID": 8015002337434856495
    },
    {
      "m_FileID": 14,
      "m_PathID": -5341164370496320169
    }
  ],
  "mEffectAreaEnv": {
    "m_FileID": 12,
    "m_PathID": -7648637488896374882
  },
  "mEffectAreaCamera": {
    "m_FileID": 19,
    "m_PathID": 1918347964618616999
  },
  "mStartGridMaterial": {
    "m_FileID": 0,
    "m_PathID": 0
  },
  "mStartGridMaterials": [
    {
      "m_FileID": 20,
      "m_PathID": 3677075346786556131
    },
    {
      "m_FileID": 2,
      "m_PathID": 8829109141535114175
    }
  ],
  "mIsOverrideStartGridParam": 0,
  "mStartGridParam": {
    "Row": 2,
    "Column": 4,
    "Width": 4.0,
    "Height": 4.0,
    "Slide1": 1.0,
    "Slide2": 2.0,
    "SlideZ": 0.0
  },
  "mCombinedMapObject": [
    {
      "m_FileID": 0,
      "m_PathID": -7769967096890926277
    },
    {
      "m_FileID": 0,
      "m_PathID": -2433976074610714050
    },
    {
      "m_FileID": 0,
      "m_PathID": 3376937574365517653
    }
  ],
  "mCourseParam": {
    "DriveSpeedRatioMin": 1.0,
    "DriveSpeedRatioMax": 1.05,
    "PosMoveTotalMin": 0.0,
    "PosMoveTotalMax": 0.0,
    "LapTimeAveMin": 0.0,
    "LapTimeAveMax": 0.0
  }
}